cordutils/__init__.py
cordutils/cordutils.py
cordutils-0.1.dist-info/METADATA
cordutils-0.1.dist-info/WHEEL
cordutils-0.1.dist-info/top_level.txt
cordutils-0.1.dist-info/RECORD
