Metadata-Version: 2.1
Name: cordutils
Version: 0.1
Requires-Dist: requests
